webrcon/__init__.py
webrcon/connector.py
webrcon/exceptions.py
webrcon/utils.py
webrcon-1.0.8.dist-info/LICENSE
webrcon-1.0.8.dist-info/METADATA
webrcon-1.0.8.dist-info/WHEEL
webrcon-1.0.8.dist-info/top_level.txt
webrcon-1.0.8.dist-info/zip-safe
webrcon-1.0.8.dist-info/RECORD
