Metadata-Version: 2.1
Name: webrcon
Version: 1.0.8
Summary: Basic async interface for Rust's WebRcon protocol
Home-page: https://github.com/lewdneko/webrcon
Author: lewdneko
License: BlueOak-1.0.0
Keywords: rust webrcon rcon websockets ws rust_game async
Platform: Windows
Platform: Linux
Platform: OSX
Requires-Python: >=3.6
